etl4py.py
etl4py-0.1.0.dist-info/LICENSE
etl4py-0.1.0.dist-info/METADATA
etl4py-0.1.0.dist-info/WHEEL
etl4py-0.1.0.dist-info/top_level.txt
etl4py-0.1.0.dist-info/RECORD
