Metadata-Version: 2.2
Name: etl4py
Version: 0.1.0
Summary: Beautiful, typesafe dataflows that scale from laptop to thousands of cores
Home-page: https://github.com/mattlianje/etl4py
Author: Matthieu Court
Author-email: matthieu.court@protonmail.com
License: GPL-3.0
Classifier: Programming Language :: Python :: 3.7
Classifier: License :: OSI Approved :: GNU General Public License v3 (GPLv3)
Requires-Python: >=3.7
License-File: LICENSE
Dynamic: author
Dynamic: author-email
Dynamic: classifier
Dynamic: description
Dynamic: description-content-type
Dynamic: home-page
Dynamic: license
Dynamic: requires-python
Dynamic: summary
